mkdocs_inline_select_svg_plugin/__init__.py
mkdocs_inline_select_svg_plugin/plugin.py
mkdocs_inline_select_svg_plugin-0.1.0.dist-info/METADATA
mkdocs_inline_select_svg_plugin-0.1.0.dist-info/WHEEL
mkdocs_inline_select_svg_plugin-0.1.0.dist-info/entry_points.txt
mkdocs_inline_select_svg_plugin-0.1.0.dist-info/licenses/LICENSE
mkdocs_inline_select_svg_plugin-0.1.0.dist-info/RECORD
