Metadata-Version: 2.1
Name: mkdocs-inline-select-svg-plugin
Version: 0.1.0
Summary: A MkDocs plugin that inlines SVG images matching a pattern into the output without inlining Materials theme icons.
Project-URL: Source, https://github.com/temperlang/svg-inline-mkdocs-plugin
Project-URL: Homepage, https://github.com/temperlang/svg-inline-mkdocs-plugin
Project-URL: Bug Tracker, https://github.com/temperlang/svg-inline-mkdocs-plugin/issues
Author-email: Mike Samuel <mikesamuel@gmail.com>
License-Expression: Apache-2.0
License-File: LICENSE
Keywords: mkdocs,mkdocs-plugin,plugin,svg
Classifier: Framework :: MkDocs
Classifier: License :: OSI Approved :: Apache Software License
Classifier: Operating System :: OS Independent
Classifier: Programming Language :: Python :: 3
Requires-Python: >=3.8
Requires-Dist: beautifulsoup4>=4.12.0
Requires-Dist: lxml>=4.9.3
Requires-Dist: mkdocs>=1.4.0
